senlin/__init__.py
senlin/version.py
senlin/api/__init__.py
senlin/api/common/__init__.py
senlin/api/common/serializers.py
senlin/api/common/util.py
senlin/api/common/version_request.py
senlin/api/common/versioned_method.py
senlin/api/common/wsgi.py
senlin/api/middleware/__init__.py
senlin/api/middleware/context.py
senlin/api/middleware/fault.py
senlin/api/middleware/trust.py
senlin/api/middleware/version_negotiation.py
senlin/api/middleware/webhook.py
senlin/api/openstack/__init__.py
senlin/api/openstack/history.rst
senlin/api/openstack/versions.py
senlin/api/openstack/v1/__init__.py
senlin/api/openstack/v1/actions.py
senlin/api/openstack/v1/build_info.py
senlin/api/openstack/v1/cluster_policies.py
senlin/api/openstack/v1/clusters.py
senlin/api/openstack/v1/events.py
senlin/api/openstack/v1/nodes.py
senlin/api/openstack/v1/policies.py
senlin/api/openstack/v1/policy_types.py
senlin/api/openstack/v1/profile_types.py
senlin/api/openstack/v1/profiles.py
senlin/api/openstack/v1/receivers.py
senlin/api/openstack/v1/router.py
senlin/api/openstack/v1/services.py
senlin/api/openstack/v1/version.py
senlin/api/openstack/v1/webhooks.py
senlin/cmd/__init__.py
senlin/cmd/api.py
senlin/cmd/api_wsgi.py
senlin/cmd/conductor.py
senlin/cmd/engine.py
senlin/cmd/health_manager.py
senlin/cmd/manage.py
senlin/cmd/status.py
senlin/common/__init__.py
senlin/common/config.py
senlin/common/constraints.py
senlin/common/consts.py
senlin/common/context.py
senlin/common/exception.py
senlin/common/i18n.py
senlin/common/messaging.py
senlin/common/policy.py
senlin/common/profiler.py
senlin/common/scaleutils.py
senlin/common/schema.py
senlin/common/service.py
senlin/common/utils.py
senlin/common/policies/__init__.py
senlin/common/policies/actions.py
senlin/common/policies/base.py
senlin/common/policies/build_info.py
senlin/common/policies/cluster_policies.py
senlin/common/policies/clusters.py
senlin/common/policies/events.py
senlin/common/policies/nodes.py
senlin/common/policies/policies.py
senlin-16.0.0.dist-info/AUTHORS
senlin-16.0.0.dist-info/LICENSE
senlin-16.0.0.dist-info/METADATA
senlin-16.0.0.dist-info/WHEEL
senlin-16.0.0.dist-info/entry_points.txt
senlin-16.0.0.dist-info/pbr.json
senlin-16.0.0.dist-info/top_level.txt
senlin-16.0.0.dist-info/RECORD
