Metadata-Version: 2.1
Name: senlin
Version: 16.0.0
Summary: OpenStack Clustering
Home-page: https://docs.openstack.org/senlin/latest/
Author: OpenStack
Author-email: openstack-discuss@lists.openstack.org
License: UNKNOWN
Platform: UNKNOWN
Classifier: Environment :: OpenStack
Classifier: Intended Audience :: Information Technology
Classifier: Intended Audience :: System Administrators
Classifier: License :: OSI Approved :: Apache Software License
Classifier: Operating System :: POSIX :: Linux
Classifier: Programming Language :: Python
Classifier: Programming Language :: Python :: 3 :: Only
Classifier: Programming Language :: Python :: 3
Classifier: Programming Language :: Python :: 3.8
Requires-Python: >=3.8
Requires-Dist: PasteDeploy (>=1.5.0)
Requires-Dist: PyYAML (>=5.1)
Requires-Dist: Routes (>=2.3.1)
Requires-Dist: SQLAlchemy (>=1.4.41)
Requires-Dist: WebOb (>=1.7.1)
Requires-Dist: alembic (>=1.6.5)
Requires-Dist: docker (>=2.4.2)
Requires-Dist: eventlet (>=0.26.1)
Requires-Dist: jsonpath-rw (>=1.4.0)
Requires-Dist: jsonschema (>=3.2.0)
Requires-Dist: keystoneauth1 (>=3.18.0)
Requires-Dist: keystonemiddleware (>=4.17.0)
Requires-Dist: microversion-parse (>=0.2.1)
Requires-Dist: openstacksdk (>=0.99.0)
Requires-Dist: oslo.config (>=6.8.0)
Requires-Dist: oslo.context (>=2.22.0)
Requires-Dist: oslo.db (>=6.0.0)
Requires-Dist: oslo.i18n (>=3.20.0)
Requires-Dist: oslo.log (>=3.36.0)
Requires-Dist: oslo.messaging (>=14.1.0)
Requires-Dist: oslo.middleware (>=3.31.0)
Requires-Dist: oslo.policy (>=3.6.0)
Requires-Dist: oslo.reports (>=1.18.0)
Requires-Dist: oslo.serialization (>=2.25.0)
Requires-Dist: oslo.service (>=1.31.0)
Requires-Dist: oslo.upgradecheck (>=1.3.0)
Requires-Dist: oslo.utils (>=4.5.0)
Requires-Dist: oslo.versionedobjects (>=1.31.2)
Requires-Dist: osprofiler (>=2.3.0)
Requires-Dist: pbr (>=3.1.1)
Requires-Dist: pytz (>=2015.7)
Requires-Dist: requests (>=2.20.0)
Requires-Dist: stevedore (>=1.20.0)
Requires-Dist: tenacity (>=6.0.0)
